Metadata-Version: 1.0
Name: XGraphic
Version: 0.2.0
Summary: Switching between nvidia and bumblebee
Home-page: https://www.github.com/erayaydin/xgraphic
Author: Eray AYDIN
Author-email: eray@labkod.com
License: LICENSE.txt
Platform: UNKNOWN
